orientations/__init__.py
orientations/orientations.py
orientations-0.3.2.dist-info/LICENSE
orientations-0.3.2.dist-info/METADATA
orientations-0.3.2.dist-info/WHEEL
orientations-0.3.2.dist-info/top_level.txt
orientations-0.3.2.dist-info/RECORD
