Metadata-Version: 2.1
Name: orientations
Version: 0.3.2
Summary: Enumerating k-connected orientations
Home-page: https://github.com/tarasyarema/orientations
Author: Taras Yarema
Author-email: tarasyarema@pm.me
License: MIT
Keywords: SageMath packaging
Platform: UNKNOWN
Classifier: Development Status :: 4 - Beta
Classifier: Topic :: Scientific/Engineering :: Mathematics
Classifier: Topic :: Scientific/Engineering :: Visualization
Requires-Dist: sage-package
Requires-Dist: sphinx
